agentinterface/__init__.py
agentinterface/ai.py
agentinterface/callback.py
agentinterface/llms.py
agentinterface/logger.py
agentinterface/shaper.py
agentinterface-1.0.0.dist-info/METADATA
agentinterface-1.0.0.dist-info/WHEEL
agentinterface-1.0.0.dist-info/entry_points.txt
agentinterface-1.0.0.dist-info/RECORD
