Metadata-Version: 2.3
Name: agentinterface
Version: 1.0.0
Summary: Agent GUIs
License: MIT
Keywords: ai,agents,interface,ui,components,protocol,selection,rendering,react,conversational,aip,magic
Author: Tyson Chan
Author-email: tyson.chan@proton.me
Requires-Python: >=3.9,<4.0
Classifier: Development Status :: 5 - Production/Stable
Classifier: Intended Audience :: Developers
Classifier: Topic :: Software Development :: Libraries :: Python Modules
Classifier: Topic :: Software Development :: User Interfaces
Classifier: Topic :: Scientific/Engineering :: Artificial Intelligence
Classifier: License :: OSI Approved :: MIT License
Classifier: Programming Language :: Python :: 3
Classifier: Programming Language :: Python :: 3.9
Classifier: Programming Language :: Python :: 3.10
Classifier: Programming Language :: Python :: 3.11
Classifier: Programming Language :: Python :: 3.12
Provides-Extra: all
Provides-Extra: anthropic
Provides-Extra: gemini
Provides-Extra: openai
Requires-Dist: anthropic (>=0.20.0) ; extra == "all"
Requires-Dist: anthropic (>=0.20.0) ; extra == "anthropic"
Requires-Dist: google-genai (>=1.29.0) ; extra == "all"
Requires-Dist: google-genai (>=1.29.0) ; extra == "gemini"
Requires-Dist: google-genai (>=1.36.0,<2.0.0)
Requires-Dist: openai (>=1.0) ; extra == "all"
Requires-Dist: openai (>=1.0) ; extra == "openai"
Requires-Dist: typing-extensions (>=4.0)
